<panel>
	<attachment_group class="vertical_arrange_autosize"/>

	<!-- Relationship With Board -->
	<container class="icon_box" id="rbrd">
		<record id="icon_properties" auto_size="" width="0" height="0" scale_picture="true"/>
		<attachment_group class="vertical_arrange_autosize" vertical_offset="6" vertical_gap="6" horizontal_inset="0" />

		<widget class="label" id="slab" auto_size="vertical" font="label" colour="text"/>
		<container height="15">
			<attachment_group class="horizontal_arrange" horizontal_alignment="left,extend" horizontal_gap="8"/>
			<widget class="value_based_picture" id="rbri" scale_picture="true" image_alignment="left" keep_aspect_ratio="true" width="73" >
				<list id="value_list">
					<record min_value="16" max_value="10000" file="icons/custom/supporter/very high" red_replacement="green 900"/>
					<record min_value="12" max_value="15" file="icons/custom/supporter/high" red_replacement="green 600"/>
					<record min_value="9" max_value="11" file="icons/custom/supporter/moderate" red_replacement="green 300"/>
					<record min_value="5" max_value="8" file="icons/custom/supporter/low" red_replacement="green 100"/>
					<record min_value="0" max_value="7" file="icons/custom/supporter/very low" red_replacement="green"/>
				</list>
			</widget>
			<widget class="text" id="sbtn" auto_size="horizontal" style="bold"/>
		</container>
	</container>

	<!-- International Reach -->
	<container class="icon_box" id="intr">
		<record id="icon_properties" auto_size="" width="0" height="0" scale_picture="true"/>
		<attachment_group class="vertical_arrange_autosize" vertical_offset="6" vertical_gap="6" horizontal_inset="0" />

		<widget class="label" id="slab" auto_size="vertical" font="label" colour="text"/>
		<container>
			<attachment_group class="horizontal_arrange_vertical_autosize" horizontal_alignment="left,extend"/>
			
			<widget class="icon_button" id="sbtn" minimum_width="100" height="20" alignment="left,centre_y" appearance="buttons/text/button" navigation_focus_target="false" auto_size="horizontal"/>
			<widget class="picture" id="ichg" scale_picture="true" auto_size="vertical" hidden="true"/>
		</container>
	</container>

	<!-- Social Media -->
	<container class="icon_box" id="socm">
		<record id="icon_properties" auto_size="" width="0" height="0" scale_picture="true"/>
		<attachment_group class="vertical_arrange_autosize" vertical_offset="6" vertical_gap="6" horizontal_inset="0" />

		<widget class="label" id="slab" auto_size="vertical" font="label" colour="text"/>
		<container>
			<attachment_group class="horizontal_arrange_vertical_autosize" horizontal_alignment="left,extend"/>
			
			<widget class="icon_button" id="sbtn" minimum_width="100" height="20" alignment="left,centre_y" appearance="buttons/text/button" navigation_focus_target="false" auto_size="horizontal"/>
			<widget class="picture" id="ichg" scale_picture="true" auto_size="vertical" hidden="true"/>
		</container>
	</container>

	<!-- Season Ticket Holders -->
	<container class="icon_box" id="stkh">
		<record id="icon_properties" auto_size="" width="0" height="0" scale_picture="true"/>
		<attachment_group class="vertical_arrange_autosize" vertical_offset="6" vertical_gap="6" horizontal_inset="0" />

		<widget class="label" id="slab" auto_size="vertical" font="label" colour="text"/>
		<container>
			<attachment_group class="horizontal_arrange_vertical_autosize" horizontal_alignment="left,extend"/>
			
			<widget class="icon_button" id="sbtn" minimum_width="100" height="20" alignment="left,centre_y" appearance="buttons/text/button" navigation_focus_target="false" auto_size="horizontal"/>
			<widget class="picture" id="ichg" scale_picture="true" auto_size="vertical" hidden="true"/>
		</container>
	</container>

	<!-- Season Ticket Waiting List -->
	<container class="icon_box" id="stwl">
		<record id="icon_properties" auto_size="" width="0" height="0" scale_picture="true"/>
		<attachment_group class="vertical_arrange_autosize" vertical_offset="6" vertical_gap="6" horizontal_inset="0" />

		<widget class="label" id="slab" auto_size="vertical" font="label" colour="text"/>
		<container>
			<attachment_group class="horizontal_arrange_vertical_autosize" horizontal_alignment="left,extend"/>
			
			<widget class="icon_button" id="sbtn" minimum_width="100" height="20" alignment="left,centre_y" appearance="buttons/text/button" navigation_focus_target="false" auto_size="horizontal"/>
			<widget class="picture" id="ichg" scale_picture="true" auto_size="vertical" hidden="true"/>
		</container>
	</container>
</panel>