<panel height="435" width="200">
	<list id="draw_order">
		<record entity_layout_id="at00" />
		<record entity_layout_id="at01" />
		<record entity_layout_id="at03" />
		<record entity_layout_id="at04" />
		<record entity_layout_id="at05" />
		<record entity_layout_id="at02" />
		<record entity_layout_id="at07" />
		<record entity_layout_id="at08" />
		<record entity_layout_id="at09" />
		<record entity_layout_id="at0&lt;" />
		<record entity_layout_id="at06" />
		<record entity_layout_id="at0:" />
		<record entity_layout_id="at0;" />
		<record entity_layout_id="at0=" />
		<record entity_layout_id="at0&gt;" />
	</list>
	<widget class="spacer" id="main">
		<boolean id="exclude_from_find" value="true" />
		<layout class="stick_to_sides_attachment" alignment="all" inset="0" />
	</widget>
	<widget class="spacer" id="fmin" embed_in_frame="true">
		<boolean id="exclude_from_find" value="true" />
		<layout class="stick_to_sides_attachment" embed_in_frame="true" alignment="all" inset="0" />
	</widget>
	<container entity_layout_id="at00" id="at00">
		<layout class="stick_to_object_attachment" id="align_top" get_side="top" set_side="top" target="main" />
		<layout class="stick_to_object_attachment" id="align_bottom" get_side="bottom" set_side="bottom" target="main" />
		<layout class="stick_to_object_attachment" id="align_left" get_side="left" set_side="left" target="main" />
		<layout class="stick_to_object_attachment" id="align_right" get_side="right" set_side="right" target="main" />
		<widget class="spacer" id="main">
			<boolean id="exclude_from_find" value="true" />
			<layout class="stick_to_sides_attachment" alignment="all" inset="0" />
		</widget>
		<widget class="spacer" id="fmin" embed_in_frame="true">
			<boolean id="exclude_from_find" value="true" />
			<layout class="stick_to_sides_attachment" embed_in_frame="true" alignment="all" inset="0" />
		</widget>
		<container entity_layout_id="at01" id="at01" height="70">
			<layout class="stick_to_object_attachment" id="align_top" get_side="top" set_side="top" move_side="true" target="main" />
			<layout class="stick_to_object_attachment" id="align_left" get_side="left" set_side="left" target="main" />
			<layout class="stick_to_object_attachment" id="align_right" get_side="right" set_side="right" target="main" />
			<widget class="spacer" id="main">
				<boolean id="exclude_from_find" value="true" />
				<layout class="stick_to_sides_attachment" alignment="all" inset="0" />
			</widget>
			<widget class="spacer" id="fmin" embed_in_frame="true">
				<boolean id="exclude_from_find" value="true" />
				<layout class="stick_to_sides_attachment" embed_in_frame="true" alignment="all" inset="0" />
			</widget>
			<widget class="person_button" colour="black" entity_layout_id="at03" id="prbt" height="25">
				<layout class="stick_to_object_attachment" id="align_top" offset="4" get_side="top" set_side="top" move_side="true" target="main" />
				<layout class="stick_to_object_attachment" id="align_left" offset="4" get_side="left" set_side="left" target="main" />
				<layout class="stick_to_object_attachment" id="align_right" get_side="right" set_side="right" target="main" />
			</widget>
			<widget class="team_button" entity_layout_id="at04" id="pTbt" height="25">
				<layout class="stick_to_object_attachment" id="align_top" offset="3" get_side="bottom" set_side="top" move_side="true" target="at03" />
				<layout class="stick_to_object_attachment" id="align_left" get_side="left" set_side="left" target="main" />
				<layout class="stick_to_object_attachment" id="align_right" get_side="right" set_side="right" target="main" />
			</widget>
			<widget class="horizontal_divider" entity_layout_id="at05" id="at05" height="2">
				<string id="image_alignment" value="centre_y" />
				<layout class="stick_to_object_attachment" id="align_bottom" get_side="bottom" set_side="bottom" move_side="true" target="main" />
				<layout class="stick_to_object_attachment" id="align_left" get_side="left" set_side="left" target="main" />
				<layout class="stick_to_object_attachment" id="align_right" get_side="right" set_side="right" target="main" />
			</widget>
		</container>
		<container entity_layout_id="at02" id="at02">
			<layout class="stick_to_object_attachment" id="align_top" offset="5" get_side="bottom" set_side="top" target="at01" />
			<layout class="stick_to_object_attachment" id="align_bottom" get_side="bottom" set_side="bottom" target="main" />
			<layout class="stick_to_object_attachment" id="align_left" get_side="left" set_side="left" target="main" />
			<layout class="stick_to_object_attachment" id="align_right" get_side="right" set_side="right" target="main" />
			<widget class="spacer" id="main">
				<boolean id="exclude_from_find" value="true" />
				<layout class="stick_to_sides_attachment" alignment="all" inset="0" />
			</widget>
			<widget class="spacer" id="fmin" embed_in_frame="true">
				<boolean id="exclude_from_find" value="true" />
				<layout class="stick_to_sides_attachment" embed_in_frame="true" alignment="all" inset="0" />
			</widget>
			<widget class="text" entity_layout_id="at07" id="at07" height="15">
				<translation id="text" translation_id="309184" type="use" value="Match Performance[COMMENT: interaction manager; category type]" />
				<string id="font" value="title" />
				<string id="colour" value="white" />
				<layout class="stick_to_object_attachment" id="align_top" offset="5" get_side="top" set_side="top" move_side="true" target="main" />
				<layout class="stick_to_object_attachment" id="align_left" get_side="left" set_side="left" target="main" />
				<layout class="stick_to_object_attachment" id="align_right" get_side="right" set_side="right" target="main" />
			</widget>
			<widget class="text" entity_layout_id="at08" id="vsTx" height="25">
				<string id="value" value="text" />
				<layout class="stick_to_object_attachment" id="align_top" offset="7" get_side="bottom" set_side="top" move_side="true" target="at07" />
				<layout class="stick_to_object_attachment" id="align_left" get_side="left" set_side="left" target="main" />
				<layout class="stick_to_object_attachment" id="align_right" get_side="right" set_side="right" target="main" />
			</widget>
						<widget class="text" entity_layout_id="at09" id="scrL" alignment="centre_x,centre_y" auto_size="horizontal" height="25">

				<string id="style" value="bold" />
				<string id="value" value="text" />
				<layout class="stick_to_object_attachment" id="align_top" offset="15" get_side="bottom" set_side="top" move_side="true" target="at08" />
				<layout class="centre_in_parent_attachment" id="align_centre_horiz" alignment="horizontal" offset="0" />
			</widget>
			<container entity_layout_id="at0&lt;" id="at0&lt;" height="35">
				<layout class="stick_to_object_attachment" id="align_top" offset="15" get_side="bottom" set_side="top" move_side="true" target="at09" />
				<layout class="stick_to_object_attachment" id="align_left" get_side="left" set_side="left" target="main" />
				<layout class="stick_to_object_attachment" id="align_right" get_side="right" set_side="right" target="main" />
				<widget class="spacer" id="main">
					<boolean id="exclude_from_find" value="true" />
					<layout class="stick_to_sides_attachment" alignment="all" inset="0" />
				</widget>
				<widget class="spacer" id="fmin" embed_in_frame="true">
					<boolean id="exclude_from_find" value="true" />
					<layout class="stick_to_sides_attachment" embed_in_frame="true" alignment="all" inset="0" />
				</widget>
				<widget class="text" id="at0&gt;" alignment="centre_y,left" entity_layout_id="at0&gt;" width="140" height="35">
					<integer id="size" value="10" />
					<translation id="text" value="Average Rating" translation_id="233158" type="use" />
					<layout class="stick_to_object_attachment" id="align_top" get_side="top" set_side="top" move_side="true" target="main" />
					<layout class="stick_to_object_attachment" id="align_left" get_side="left" set_side="left" move_side="true" target="main" />
				</widget>
				<widget class="match_rating_label_formatted" entity_layout_id="at0=" id="rati" format="[%fraction#1-3.2]">
					<layout class="stick_to_object_attachment" id="align_top" get_side="top" set_side="top" target="main" />
					<layout class="stick_to_object_attachment" id="align_bottom" get_side="bottom" set_side="bottom" target="main" />
					<layout class="stick_to_object_attachment" id="align_left" get_side="right" set_side="left" target="at0&gt;" />
					<layout class="stick_to_object_attachment" id="align_right" get_side="right" set_side="right" target="main" />
				</widget>
			</container>
			<container class="table" entity_layout_id="at06" id="staT" layout="140,-1" mode="fill_rows, stripe_rows">
				<list id="column_table_properties">
					<record>
						<integer id="index" value="0" />
						<record id="widget_info" class="text" />
					</record>
					<record>
						<integer id="index" value="1" />
						<record id="widget_info" class="text" />
					</record>
				</list>
				<list id="column_widget_properties">
					<record index="0" alignment="left,centre_y" size="10" />
					<record index="1" alignment="centre" size="10" style="semi_bold" />
				</list>
				<integer id="row_height" value="35" />
				<string id="auto_size_rows" value="false" />
				<string id="fixed_size_rows" value="true" />
				<layout class="stick_to_object_attachment" id="align_top" get_side="bottom" set_side="top" target="at0&lt;" />
				<layout class="stick_to_object_attachment" id="align_bottom" get_side="bottom" set_side="bottom" target="main" />
				<layout class="stick_to_object_attachment" id="align_left" get_side="left" set_side="left" target="main" />
				<layout class="stick_to_object_attachment" id="align_right" get_side="right" set_side="right" target="main" />
			</container>
			<container class="object_portrait_picture" entity_layout_id="at0:" id="HmOP" width="30" height="30">
				<string id="image_alignment" value="centre" />
				<string id="scale_picture" value="true" />
				<string id="keep_aspect_ratio" value="true" />
				<string id="no_object_picture" value="pictures/logos/normal/clubs/cro/dinamo zagreb" />
				<layout class="stick_to_object_attachment" id="align_top" offset="10" get_side="bottom" set_side="top" move_side="true" target="at08" />
				<layout class="stick_to_object_attachment" id="align_right" offset="-10" get_side="left" set_side="right" move_side="true" target="at09" />
			</container>
			<container class="object_portrait_picture" entity_layout_id="at0;" id="AwOP" width="30" height="30">
				<string id="image_alignment" value="centre" />
				<string id="scale_picture" value="true" />
				<string id="keep_aspect_ratio" value="true" />
				<string id="no_object_picture" value="pictures/logos/normal/clubs/cro/dinamo zagreb" />
				<layout class="stick_to_object_attachment" id="align_top" offset="10" get_side="bottom" set_side="top" move_side="true" target="at08" />
				<layout class="stick_to_object_attachment" id="align_left" offset="10" get_side="right" set_side="left" move_side="true" target="at09" />
			</container>
		</container>
	</container>
</panel>